django-brstocks/__init__.py
django-brstocks/admin.py
django-brstocks/apps.py
django-brstocks/models.py
django-brstocks/stocks_tests.py
django-brstocks/tests.py
django-brstocks/urls.py
django-brstocks/views.py
django-brstocks/api/__init__.py
django-brstocks/api/serializers.py
django-brstocks/migrations/__init__.py
django-brstocks/stocks/__init__.py
django-brstocks/stocks/models.py
django-brstocks/templates/investments/index.html
django-brstocks/templates/investments/stocks.html
django_brstocks/__init__.py
django_brstocks/admin.py
django_brstocks/apps.py
django_brstocks/models.py
django_brstocks/stocks_tests.py
django_brstocks/tests.py
django_brstocks/urls.py
django_brstocks/views.py
django_brstocks/api/__init__.py
django_brstocks/api/serializers.py
django_brstocks/migrations/__init__.py
django_brstocks/stocks/__init__.py
django_brstocks/stocks/models.py
django_brstocks-0.5.dist-info/DESCRIPTION.rst
django_brstocks-0.5.dist-info/METADATA
django_brstocks-0.5.dist-info/RECORD
django_brstocks-0.5.dist-info/WHEEL
django_brstocks-0.5.dist-info/metadata.json
django_brstocks-0.5.dist-info/top_level.txt
