Metadata-Version: 2.0
Name: django-brstocks
Version: 0.5
Summary: A simple Django app to track Stocks on Brazilian Stock Market
Home-page: https://www.github.com/ebratz/django-brstocks
Author: Eduardo Bratz
Author-email: ebratz@gmail.com
License: BSD License
Platform: UNKNOWN
Classifier: Environment :: Web Environment
Classifier: Framework :: Django
Classifier: Framework :: Django :: 2.0
Classifier: Intended Audience :: Developers
Classifier: License :: OSI Approved :: BSD License
Classifier: Operating System :: OS Independent
Classifier: Programming Language :: Python
Classifier: Programming Language :: Python :: 3.5
Classifier: Programming Language :: Python :: 3.6
Classifier: Topic :: Internet :: WWW/HTTP
Classifier: Topic :: Internet :: WWW/HTTP :: Dynamic Content
